{
  "boot-core": {
    "file": "boot-core.bundle.f19e7ae8e307.js",
    "hash": "f19e7ae8e307",
    "sourceFingerprint": "9ca4759c8a55",
    "fileCount": 39,
    "size": 1076429,
    "builtAt": "2026-06-10T17:28:57.263Z"
  },
  "boot-calc": {
    "file": "boot-calc.bundle.86df303fccb3.js",
    "hash": "86df303fccb3",
    "sourceFingerprint": "f27cc076d9cf",
    "fileCount": 19,
    "size": 719377,
    "builtAt": "2026-06-10T17:28:59.328Z"
  },
  "boot-day": {
    "file": "boot-day.bundle.4386c636b0b8.js",
    "hash": "4386c636b0b8",
    "sourceFingerprint": "48fdc4f506bb",
    "fileCount": 58,
    "size": 575809,
    "builtAt": "2026-06-10T17:29:00.768Z"
  },
  "boot-app": {
    "file": "boot-app.bundle.35394fe51fe3.js",
    "hash": "35394fe51fe3",
    "sourceFingerprint": "a81fd7b7df3c",
    "fileCount": 51,
    "size": 972431,
    "builtAt": "2026-06-10T17:29:03.311Z"
  },
  "boot-init": {
    "file": "boot-init.bundle.6ccbd951db49.js",
    "hash": "6ccbd951db49",
    "sourceFingerprint": "97697b9b5736",
    "fileCount": 6,
    "size": 20245,
    "builtAt": "2026-06-10T17:29:03.449Z"
  },
  "postboot-1-game-eager": {
    "file": "postboot-1-game-eager.bundle.ec3e720f3597.js",
    "hash": "ec3e720f3597",
    "sourceFingerprint": "db9e5da88a76",
    "fileCount": 1,
    "size": 1369,
    "builtAt": "2026-06-10T17:29:03.533Z"
  },
  "postboot-1-game-lazy": {
    "file": "postboot-1-game-lazy.bundle.40851784f61a.js",
    "hash": "40851784f61a",
    "sourceFingerprint": "c55fd9eb7cbb",
    "fileCount": 32,
    "size": 1488451,
    "builtAt": "2026-06-10T17:29:06.783Z"
  },
  "postboot-2-insights-eager": {
    "file": "postboot-2-insights-eager.bundle.807cb783ab2f.js",
    "hash": "807cb783ab2f",
    "sourceFingerprint": "f6b773bd8a27",
    "fileCount": 1,
    "size": 1524,
    "builtAt": "2026-06-10T17:29:06.869Z"
  },
  "postboot-2-insights-lazy": {
    "file": "postboot-2-insights-lazy.bundle.88c1c3bf1c73.js",
    "hash": "88c1c3bf1c73",
    "sourceFingerprint": "03acfa8effb3",
    "fileCount": 39,
    "size": 1644579,
    "builtAt": "2026-06-10T17:29:09.496Z"
  },
  "postboot-3-ui-eager": {
    "file": "postboot-3-ui-eager.bundle.c8fad97e55d3.js",
    "hash": "c8fad97e55d3",
    "sourceFingerprint": "d9aac19a5fe4",
    "fileCount": 2,
    "size": 3880,
    "builtAt": "2026-06-10T17:29:09.605Z"
  },
  "postboot-3-ui-lazy": {
    "file": "postboot-3-ui-lazy.bundle.a924f3952049.js",
    "hash": "a924f3952049",
    "sourceFingerprint": "6b0bef5e181c",
    "fileCount": 51,
    "size": 2057413,
    "builtAt": "2026-06-10T17:29:14.369Z"
  }
}
