{
  "postboot-1-game-lazy": {
    "file": "postboot-1-game-lazy.bundle.1746e88750eb.js",
    "hash": "1746e88750eb",
    "sourceFingerprint": "1c4e0bfe163a",
    "fileCount": 32,
    "size": 1392630,
    "builtAt": "2026-05-28T10:03:52.337Z"
  },
  "postboot-2-insights-lazy": {
    "file": "postboot-2-insights-lazy.bundle.f7b436c457ff.js",
    "hash": "f7b436c457ff",
    "sourceFingerprint": "fc44e935ce5d",
    "fileCount": 39,
    "size": 1640450,
    "builtAt": "2026-05-28T10:03:54.878Z"
  },
  "postboot-3-ui-lazy": {
    "file": "postboot-3-ui-lazy.bundle.a8ff2560b7ff.js",
    "hash": "a8ff2560b7ff",
    "sourceFingerprint": "cb6a63127471",
    "fileCount": 50,
    "size": 1902061,
    "builtAt": "2026-05-28T10:03:59.145Z"
  }
}