{
  "releases": [
    {
      "version": "2026.06.18.95cfefc1",
      "buildHash": "95cfefc1",
      "date": "2026-06-18",
      "kind": "user-facing",
      "profile": "user-facing-general",
      "title": "Голосовые сообщения стали устойчивее",
      "items": [
        {
          "type": "fix",
          "title": "Расшифровка голосовых стала устойчивее",
          "description": "Если во время обработки был краткий сбой сервиса или согласие включили после отправки, приложение аккуратнее продолжает расшифровку вместо ошибки."
        }
      ],
      "coveredCommits": ["95cfefc1", "fc18e6ea", "16e2a030", "db3c9d86"]
    },
    {
      "version": "2026.06.18.5ec7b239",
      "buildHash": "5ec7b239",
      "date": "2026-06-18",
      "kind": "user-facing",
      "profile": "user-facing-general",
      "title": "Голосовые с расшифровкой",
      "items": [
        {
          "type": "feat",
          "title": "Добавили пилот расшифровки голосовых",
          "description": "Голосовые сообщения теперь готовятся к автоматической расшифровке через Yandex SpeechKit: перед первой расшифровкой запрашивается согласие, а текст появляется под плеером после обработки."
        }
      ],
      "coveredCommits": ["5ec7b239"]
    },
    {
      "version": "2026.06.18.a72c5486",
      "buildHash": "a72c5486",
      "date": "2026-06-18",
      "kind": "technical",
      "profile": "technical-backend-api",
      "title": "Telegram-боты стали устойчивее",
      "items": [
        {
          "type": "fix",
          "title": "Telegram-боты стабильнее освобождают обработку",
          "description": "После короткого polling-цикла бот корректнее завершает работу с базой и освобождает очередь обработки. Это снижает риск зависших повторных запусков."
        }
      ],
      "coveredCommits": ["a72c5486"]
    },
    {
      "version": "2026.06.18.e4db35e3",
      "buildHash": "e4db35e3",
      "date": "2026-06-18",
      "kind": "user-facing",
      "profile": "user-facing-general",
      "title": "Кабинет куратора и поддержка стали устойчивее",
      "items": [
        {
          "type": "fix",
          "title": "Чаты и кабинет куратора стали устойчивее",
          "description": "Приложение корректнее различает вход клиента и куратора. Сообщения с фото и голосом стабильнее отправляются и обновляются в рабочих сценариях."
        },
        {
          "type": "fix",
          "title": "Поддержка открывается в рабочем боте",
          "description": "Контакты поддержки в документах и экранах оплаты ведут на актуального Telegram-бота. Это помогает быстрее попасть в правильный канал обращения."
        }
      ],
      "coveredCommits": ["e4db35e3", "955f21e8"]
    },
    {
      "version": "2026.06.18.82764b6d",
      "buildHash": "82764b6d",
      "date": "2026-06-18",
      "kind": "user-facing",
      "profile": "user-facing-general",
      "title": "Обновлена мобильная навигация и активность",
      "items": [
        {
          "type": "fix",
          "title": "Активность и отчёты стали понятнее",
          "description": "Карточки активности, тренировок и зарядки собраны в отдельную вкладку; отчёты по неделям и месяцам открываются из раздела отчётов."
        }
      ]
    },
    {
      "version": "2026.06.17.1fcff1a8",
      "buildHash": "1fcff1a8",
      "date": "2026-06-17",
      "kind": "user-facing",
      "profile": "user-facing-general",
      "title": "Хронометраж стал устойчивее",
      "items": [
        {
          "type": "fix",
          "title": "Хронометраж открывается без сбоя",
          "description": "Исправили сбой, который мог появляться при открытии хронометража после обновления записей. Теперь экран корректно показывает сводку, записи и круги активностей в таких переходах."
        }
      ],
      "coveredCommits": ["1fcff1a8"]
    },
    {
      "version": "2026.06.17.65fcbd6c",
      "buildHash": "65fcbd6c",
      "date": "2026-06-17",
      "kind": "user-facing",
      "profile": "user-facing-general",
      "title": "Тренировки и дневник стали устойчивее",
      "items": [
        {
          "type": "fix",
          "title": "Продолжение тренировки стало надёжнее",
          "description": "Если сессия прервалась или страница была перезагружена, приложение аккуратнее восстанавливает активную тренировку и защищает её от параллельного запуска в другой вкладке."
        },
        {
          "type": "fix",
          "title": "Наборы продуктов добавляются корректнее",
          "description": "При добавлении нескольких продуктов из готового набора дневник сохраняет весь список за один шаг и корректно обновляет расчёты."
        },
        {
          "type": "fix",
          "title": "История порций разделяется точнее",
          "description": "Дневник больше не сохраняет историю введённых граммов в общий контур, если данные клиента ещё не готовы. Это помогает не смешивать подсказки порций между разными клиентами."
        }
      ],
      "coveredCommits": ["fc04b12a", "1246e6ba", "65fcbd6c"]
    },
    {
      "version": "2026.06.17.046d3be2",
      "buildHash": "046d3be2",
      "date": "2026-06-17",
      "kind": "user-facing",
      "profile": "user-facing-general",
      "title": "Надёжность подготовки приложения",
      "items": [
        {
          "type": "fix",
          "title": "Проверки перед запуском стали устойчивее",
          "description": "Обновлены служебные компоненты, которые помогают заранее находить риски перед выпуском. Пользовательские сценарии не изменились."
        }
      ]
    },
    {
      "version": "2026.06.17.d8e616d5",
      "buildHash": "d8e616d5",
      "date": "2026-06-17",
      "kind": "user-facing",
      "profile": "user-facing-general",
      "title": "План запуска стал нагляднее",
      "items": [
        {
          "type": "fix",
          "title": "Дашборд показывает полный план запуска",
          "description": "В маркетинговом дашборде теперь виден полный план работ с понятной подсветкой: что уже закрыто, что можно сделать силами Codex и где нужно участие основателя."
        }
      ]
    },
    {
      "version": "2026.06.17.1be0d14b",
      "buildHash": "1be0d14b",
      "date": "2026-06-17",
      "kind": "user-facing",
      "profile": "user-facing-general",
      "title": "Улучшена повторная Telegram-привязка",
      "items": [
        {
          "type": "fix",
          "title": "Ссылка для повторной привязки клиента",
          "description": "После сброса Telegram-привязки куратор может снова скопировать действующую ссылку клиента; если ссылка истекла, интерфейс предлагает перевыпустить PIN и ссылку."
        }
      ],
      "coveredCommits": ["1be0d14b"]
    }
  ]
}
